vsadmin/__init__.py
vsadmin/cli.py
vsadmin/commands/__init__.py
vsadmin/commands/cmd_search.py
vsadmin/commands/tools.py
vsadmin-0.0.1.dist-info/DESCRIPTION.rst
vsadmin-0.0.1.dist-info/METADATA
vsadmin-0.0.1.dist-info/RECORD
vsadmin-0.0.1.dist-info/WHEEL
vsadmin-0.0.1.dist-info/entry_points.txt
vsadmin-0.0.1.dist-info/metadata.json
vsadmin-0.0.1.dist-info/top_level.txt
