Metadata-Version: 2.0
Name: vsadmin
Version: 0.0.1
Summary: Command line interface to Vmware vSphere.
Home-page: https://github.com/verdel/vsadmin
Author: Vadim Aleksandrov
Author-email: valeksandrov@me.com
License: MIT
Keywords: vsadmin
Platform: UNKNOWN
Classifier: Development Status :: 2 - Pre-Alpha
Classifier: Intended Audience :: Developers
Classifier: License :: OSI Approved :: MIT License
Classifier: Natural Language :: English
Classifier: Programming Language :: Python :: 2
Classifier: Programming Language :: Python :: 2.7
Classifier: Programming Language :: Python :: 3
Classifier: Programming Language :: Python :: 3.3
Classifier: Programming Language :: Python :: 3.4
Classifier: Programming Language :: Python :: 3.5
Requires-Dist: click
Requires-Dist: pyvmomi
Requires-Dist: requests
